dirlib.py
dirlib-1.2.0.dist-info/LICENSE
dirlib-1.2.0.dist-info/METADATA
dirlib-1.2.0.dist-info/WHEEL
dirlib-1.2.0.dist-info/RECORD
