Metadata-Version: 2.1
Name: dirlib
Version: 1.2.0
Summary: 
Home-page: https://github.com/owlinux1000/dirlib
License: MIT
Author: owlinux1000
Author-email: encry1024@gmail.com
Requires-Python: >=3.10,<4.0
Classifier: License :: OSI Approved :: MIT License
Classifier: Programming Language :: Python :: 3
Classifier: Programming Language :: Python :: 3.10
Classifier: Programming Language :: Python :: 3.11
Project-URL: Repository, https://github.com/owlinux1000/dirlib
